sphinxcontrib_verilog_diagrams/__init__.py
sphinxcontrib_verilog_diagrams-0.1.1.dist-info/METADATA
sphinxcontrib_verilog_diagrams-0.1.1.dist-info/WHEEL
sphinxcontrib_verilog_diagrams-0.1.1.dist-info/top_level.txt
sphinxcontrib_verilog_diagrams-0.1.1.dist-info/RECORD
