Metadata-Version: 2.1
Name: sphinxcontrib-verilog-diagrams
Version: 0.1.1
Summary: Compatibility stub for renamed to sphinxcontrib-hdl-diagrams.
Home-page: https://github.com/SymbiFlow/sphinxcontrib-hdl-diagrams
Author: The SymbiFlow Authors
Author-email: symbiflow@lists.librecores.org
License: Apache 2.0
Requires-Dist: sphinxcontrib-hdl-diagrams
